{
"train_config": {"env_name": "bernoulli-bandit",
                 "device_name": "cpu",
                 "train_bandit_type": "dependent-easy",
                 "test_bandit_type": "dependent-easy",
                 "log_every_episodes": 50,
                 "test_num_episodes": 5,
                 "num_arms": 2,
                 "num_workers": 2,
                 "sync_grads": 1,
                 "threads_per_worker": 1,
                 "use_bootstrap": 1,
                 "train_lifetime": 100,
                 "test_lifetime": 100,
                 "train_num_episodes": 20000,
                 "seed_id": 0,
                 "l_rate": 0.005,
                 "l2_decay": 0.0,
                 "clip_grad_norm": 10,
                 "value_beta": 0.05,
                 "max_discount_factor": 0.8,
                 "min_discount_factor": 0.8,
                 "anneal_discount_in": 1.0,
                 "max_beta_entropy": 1,
                 "min_beta_entropy": 1e-10,
                 "anneal_entropy_in": 0.7
                  },
"log_config": {"time_to_track": ["num_episodes", "num_steps"],
               "what_to_track": ["total_loss", "actor_loss", "critic_loss",
                                 "entropy_loss", "ep_reward",
                                 "ep_regret", "ep_subopt_pulls"],
               "time_to_print": ["num_episodes", "time_elapsed"],
               "what_to_print": ["total_loss", "critic_loss",
                                 "ep_regret", "ep_subopt_pulls"],
               "use_tboard": 1,
               "overwrite_experiment_dir": 1,
               "print_every_k_updates": 10,
               "save_every_k_ckpt": 100},
"net_config": {"input_dim": 4,
               "hidden_dim": 48,
               "num_layers": 1,
               "output_dim": 2}
}
